merakicommons/__init__.py
merakicommons/cache.py
merakicommons/container.py
merakicommons/ghost.py
merakicommons/ratelimits.py
tests/__init__.py
tests/test_cache.py
tests/test_container.py
tests/test_ghost.py
tests/test_ratelimits.py
merakicommons-1.0.10.dist-info/LICENSE
merakicommons-1.0.10.dist-info/METADATA
merakicommons-1.0.10.dist-info/WHEEL
merakicommons-1.0.10.dist-info/top_level.txt
merakicommons-1.0.10.dist-info/zip-safe
merakicommons-1.0.10.dist-info/RECORD
